emmaemb/__init__.py
emmaemb/config.py
emmaemb/core.py
emmaemb/functions.py
emmaemb/test.py
emmaemb/vizualisation.py
emmaemb-1.1.6.dist-info/METADATA
emmaemb-1.1.6.dist-info/WHEEL
emmaemb-1.1.6.dist-info/licenses/LICENSE
emmaemb-1.1.6.dist-info/RECORD
