Metadata-Version: 2.4
Name: emmaemb
Version: 1.1.6
Summary: A library for comparing embedding spaces
Project-URL: Homepage, https://github.com/broadinstitute/emmaemb
Project-URL: Issues, https://github.com/broadinstitute/emmaemb/issues
Author-email: Francesca Rissom <francesca.rissom@hpi.de>, Paulo Yanez Sarmiento <paul.yanze@hpi.de>, Jordan Safer <jsafer@broadinstitute.org>
License-File: LICENSE
Classifier: License :: OSI Approved :: MIT License
Classifier: Operating System :: OS Independent
Classifier: Programming Language :: Python :: 3
Requires-Python: <3.13,>=3.8
Requires-Dist: annoy>=1.17.3
Requires-Dist: importlib-metadata>=8.5.0
Requires-Dist: joblib>=1.4.2
Requires-Dist: narwhals>=1.24.1
Requires-Dist: numpy>=1.23
Requires-Dist: packaging>=24.2
Requires-Dist: pandas>=2.0
Requires-Dist: patsy>=1.0.1
Requires-Dist: plotly-express>=0.4.1
Requires-Dist: plotly>=6.0.0
Requires-Dist: pynndescent>=0.5.13
Requires-Dist: python-dateutil>=2.9.0.post0
Requires-Dist: pytz>=2024.2
Requires-Dist: scikit-learn>=1.3
Requires-Dist: scipy>=1.10.1
Requires-Dist: six>=1.17.0
Requires-Dist: statsmodels>=0.14.1
Requires-Dist: threadpoolctl>=3.5.0
Requires-Dist: torch>=2.0
Requires-Dist: tqdm>=4.67.1
Requires-Dist: tzdata>=2025.1
Requires-Dist: umap-learn>=0.5.7
Requires-Dist: zipp>=3.20.2
